MANIFEST.in
README.txt
setup.cfg
setup.py
docs/HISTORY.txt
horae/__init__.py
horae.reports.egg-info/PKG-INFO
horae.reports.egg-info/SOURCES.txt
horae.reports.egg-info/dependency_links.txt
horae.reports.egg-info/entry_points.txt
horae.reports.egg-info/namespace_packages.txt
horae.reports.egg-info/not-zip-safe
horae.reports.egg-info/requires.txt
horae.reports.egg-info/top_level.txt
horae/reports/__init__.py
horae/reports/configure.zcml
horae/reports/interfaces.py
horae/reports/reports.py
horae/reports/traversal.py
horae/reports/viewlets.py
horae/reports/views.py
horae/reports/vocabulary.py
horae/reports/locales/horae.reports.pot
horae/reports/locales/de/LC_MESSAGES/horae.reports.mo
horae/reports/locales/de/LC_MESSAGES/horae.reports.po
horae/reports/templates/report.cpt
horae/reports/viewlet_templates/createreport.cpt