Metadata-Version: 1.0
Name: horae.reports
Version: 1.0a1
Summary: Provides basic reporting functionality for horae
Home-page: UNKNOWN
Author: Simon Kaeser
Author-email: skaeser@gmail.com
License: GPL
Platform: UNKNOWN
Classifier: Programming Language :: Python
